dfauditor/__init__.py
dfauditor/app_logger.py
dfauditor/auditor.py
dfauditor/extractor.py
dfauditor/measures.py
dfauditor/metrics.py
dfauditor/response.py
spatialedge_analytics_dfauditor-1.1.0.dist-info/LICENSE
spatialedge_analytics_dfauditor-1.1.0.dist-info/METADATA
spatialedge_analytics_dfauditor-1.1.0.dist-info/WHEEL
spatialedge_analytics_dfauditor-1.1.0.dist-info/RECORD
