Metadata-Version: 2.1
Name: spatialedge-analytics-dfauditor
Version: 1.1.0
Summary: A dataframe auditor that extracts descriptive statistics from dataframe columns
Home-page: https://gitlab.com/spatialedge/ml-engineering/dataframe-auditor
License: Spatialedge Community License
Keywords: analytics,utilities
Author: Jacques du Toit, Carl du Plessis, Jean Naude
Requires-Python: >=3.9,<3.12
Classifier: Environment :: Console
Classifier: Intended Audience :: Developers
Classifier: License :: Other/Proprietary License
Classifier: Programming Language :: Python :: 3
Classifier: Programming Language :: Python :: 3.9
Classifier: Programming Language :: Python :: 3.10
Classifier: Programming Language :: Python :: 3.11
Classifier: Topic :: Scientific/Engineering :: Information Analysis
Classifier: Topic :: Utilities
Requires-Dist: pandas (>=2.2.0,<3.0.0)
Requires-Dist: psutil (>=6.1.0,<7.0.0)
Requires-Dist: scipy (>=1.10.1,<1.14.0) ; python_version < "3.10"
Requires-Dist: scipy (>=1.14.0,<2.0.0) ; python_version >= "3.10"
Requires-Dist: twine (>=6.0.1,<7.0.0)
Project-URL: Repository, https://gitlab.com/spatialedge/ml-engineering/dataframe-auditor
